consul/__init__.py
consul/aio.py
consul/base.py
consul/std.py
consul/tornado.py
consul/twisted.py
nsof_python_consul-1.0.0.dist-info/DESCRIPTION.rst
nsof_python_consul-1.0.0.dist-info/METADATA
nsof_python_consul-1.0.0.dist-info/RECORD
nsof_python_consul-1.0.0.dist-info/WHEEL
nsof_python_consul-1.0.0.dist-info/metadata.json
nsof_python_consul-1.0.0.dist-info/top_level.txt
